{
  "type": "GROUP",
"name": "All Requests",
"path": "",
"pathFormatted": "group_missing-name-b06d1",
"stats": {
    "name": "All Requests",
    "numberOfRequests": {
        "total": 66,
        "ok": 66,
        "ko": 0
    },
    "minResponseTime": {
        "total": 20,
        "ok": 20,
        "ko": 0
    },
    "maxResponseTime": {
        "total": 78,
        "ok": 78,
        "ko": 0
    },
    "meanResponseTime": {
        "total": 30,
        "ok": 30,
        "ko": 0
    },
    "standardDeviation": {
        "total": 11,
        "ok": 11,
        "ko": 0
    },
    "percentiles1": {
        "total": 27,
        "ok": 27,
        "ko": 0
    },
    "percentiles2": {
        "total": 30,
        "ok": 30,
        "ko": 0
    },
    "percentiles3": {
        "total": 60,
        "ok": 60,
        "ko": 0
    },
    "percentiles4": {
        "total": 68,
        "ok": 68,
        "ko": 0
    },
    "group1": {
    "name": "t < 800 ms",
    "count": 66,
    "percentage": 100
},
    "group2": {
    "name": "t ≥ 800 ms <br> t < 1200 ms",
    "count": 0,
    "percentage": 0
},
    "group3": {
    "name": "t ≥ 1200 ms",
    "count": 0,
    "percentage": 0
},
    "group4": {
    "name": "failed",
    "count": 0,
    "percentage": 0
},
    "meanNumberOfRequestsPerSecond": {
        "total": 2.64,
        "ok": 2.64,
        "ko": 0
    }
},
"contents": {
"req_get-all-video-g-6a25e": {
        "type": "REQUEST",
        "name": "Get all video games",
"path": "Get all video games",
"pathFormatted": "req_get-all-video-g-6a25e",
"stats": {
    "name": "Get all video games",
    "numberOfRequests": {
        "total": 16,
        "ok": 16,
        "ko": 0
    },
    "minResponseTime": {
        "total": 21,
        "ok": 21,
        "ko": 0
    },
    "maxResponseTime": {
        "total": 78,
        "ok": 78,
        "ko": 0
    },
    "meanResponseTime": {
        "total": 36,
        "ok": 36,
        "ko": 0
    },
    "standardDeviation": {
        "total": 20,
        "ok": 20,
        "ko": 0
    },
    "percentiles1": {
        "total": 24,
        "ok": 24,
        "ko": 0
    },
    "percentiles2": {
        "total": 59,
        "ok": 59,
        "ko": 0
    },
    "percentiles3": {
        "total": 67,
        "ok": 67,
        "ko": 0
    },
    "percentiles4": {
        "total": 76,
        "ok": 76,
        "ko": 0
    },
    "group1": {
    "name": "t < 800 ms",
    "count": 16,
    "percentage": 100
},
    "group2": {
    "name": "t ≥ 800 ms <br> t < 1200 ms",
    "count": 0,
    "percentage": 0
},
    "group3": {
    "name": "t ≥ 1200 ms",
    "count": 0,
    "percentage": 0
},
    "group4": {
    "name": "failed",
    "count": 0,
    "percentage": 0
},
    "meanNumberOfRequestsPerSecond": {
        "total": 0.64,
        "ok": 0.64,
        "ko": 0
    }
}
    },"req_authenticate-ea80a": {
        "type": "REQUEST",
        "name": "Authenticate",
"path": "Authenticate",
"pathFormatted": "req_authenticate-ea80a",
"stats": {
    "name": "Authenticate",
    "numberOfRequests": {
        "total": 14,
        "ok": 14,
        "ko": 0
    },
    "minResponseTime": {
        "total": 20,
        "ok": 20,
        "ko": 0
    },
    "maxResponseTime": {
        "total": 34,
        "ok": 34,
        "ko": 0
    },
    "meanResponseTime": {
        "total": 27,
        "ok": 27,
        "ko": 0
    },
    "standardDeviation": {
        "total": 4,
        "ok": 4,
        "ko": 0
    },
    "percentiles1": {
        "total": 28,
        "ok": 28,
        "ko": 0
    },
    "percentiles2": {
        "total": 29,
        "ok": 29,
        "ko": 0
    },
    "percentiles3": {
        "total": 33,
        "ok": 33,
        "ko": 0
    },
    "percentiles4": {
        "total": 34,
        "ok": 34,
        "ko": 0
    },
    "group1": {
    "name": "t < 800 ms",
    "count": 14,
    "percentage": 100
},
    "group2": {
    "name": "t ≥ 800 ms <br> t < 1200 ms",
    "count": 0,
    "percentage": 0
},
    "group3": {
    "name": "t ≥ 1200 ms",
    "count": 0,
    "percentage": 0
},
    "group4": {
    "name": "failed",
    "count": 0,
    "percentage": 0
},
    "meanNumberOfRequestsPerSecond": {
        "total": 0.56,
        "ok": 0.56,
        "ko": 0
    }
}
    },"req_create-new-game-17c84": {
        "type": "REQUEST",
        "name": "Create New Game - Tetris",
"path": "Create New Game - Tetris",
"pathFormatted": "req_create-new-game-17c84",
"stats": {
    "name": "Create New Game - Tetris",
    "numberOfRequests": {
        "total": 4,
        "ok": 4,
        "ko": 0
    },
    "minResponseTime": {
        "total": 26,
        "ok": 26,
        "ko": 0
    },
    "maxResponseTime": {
        "total": 30,
        "ok": 30,
        "ko": 0
    },
    "meanResponseTime": {
        "total": 28,
        "ok": 28,
        "ko": 0
    },
    "standardDeviation": {
        "total": 2,
        "ok": 2,
        "ko": 0
    },
    "percentiles1": {
        "total": 27,
        "ok": 27,
        "ko": 0
    },
    "percentiles2": {
        "total": 28,
        "ok": 28,
        "ko": 0
    },
    "percentiles3": {
        "total": 30,
        "ok": 30,
        "ko": 0
    },
    "percentiles4": {
        "total": 30,
        "ok": 30,
        "ko": 0
    },
    "group1": {
    "name": "t < 800 ms",
    "count": 4,
    "percentage": 100
},
    "group2": {
    "name": "t ≥ 800 ms <br> t < 1200 ms",
    "count": 0,
    "percentage": 0
},
    "group3": {
    "name": "t ≥ 1200 ms",
    "count": 0,
    "percentage": 0
},
    "group4": {
    "name": "failed",
    "count": 0,
    "percentage": 0
},
    "meanNumberOfRequestsPerSecond": {
        "total": 0.16,
        "ok": 0.16,
        "ko": 0
    }
}
    },"req_create-new-game-a757a": {
        "type": "REQUEST",
        "name": "Create New Game - Super Mario 64",
"path": "Create New Game - Super Mario 64",
"pathFormatted": "req_create-new-game-a757a",
"stats": {
    "name": "Create New Game - Super Mario 64",
    "numberOfRequests": {
        "total": 3,
        "ok": 3,
        "ko": 0
    },
    "minResponseTime": {
        "total": 25,
        "ok": 25,
        "ko": 0
    },
    "maxResponseTime": {
        "total": 33,
        "ok": 33,
        "ko": 0
    },
    "meanResponseTime": {
        "total": 28,
        "ok": 28,
        "ko": 0
    },
    "standardDeviation": {
        "total": 3,
        "ok": 3,
        "ko": 0
    },
    "percentiles1": {
        "total": 27,
        "ok": 27,
        "ko": 0
    },
    "percentiles2": {
        "total": 30,
        "ok": 30,
        "ko": 0
    },
    "percentiles3": {
        "total": 32,
        "ok": 32,
        "ko": 0
    },
    "percentiles4": {
        "total": 33,
        "ok": 33,
        "ko": 0
    },
    "group1": {
    "name": "t < 800 ms",
    "count": 3,
    "percentage": 100
},
    "group2": {
    "name": "t ≥ 800 ms <br> t < 1200 ms",
    "count": 0,
    "percentage": 0
},
    "group3": {
    "name": "t ≥ 1200 ms",
    "count": 0,
    "percentage": 0
},
    "group4": {
    "name": "failed",
    "count": 0,
    "percentage": 0
},
    "meanNumberOfRequestsPerSecond": {
        "total": 0.12,
        "ok": 0.12,
        "ko": 0
    }
}
    },"req_get-single-game-66064": {
        "type": "REQUEST",
        "name": "Get single game - Tetris",
"path": "Get single game - Tetris",
"pathFormatted": "req_get-single-game-66064",
"stats": {
    "name": "Get single game - Tetris",
    "numberOfRequests": {
        "total": 4,
        "ok": 4,
        "ko": 0
    },
    "minResponseTime": {
        "total": 21,
        "ok": 21,
        "ko": 0
    },
    "maxResponseTime": {
        "total": 37,
        "ok": 37,
        "ko": 0
    },
    "meanResponseTime": {
        "total": 28,
        "ok": 28,
        "ko": 0
    },
    "standardDeviation": {
        "total": 6,
        "ok": 6,
        "ko": 0
    },
    "percentiles1": {
        "total": 28,
        "ok": 28,
        "ko": 0
    },
    "percentiles2": {
        "total": 31,
        "ok": 31,
        "ko": 0
    },
    "percentiles3": {
        "total": 36,
        "ok": 36,
        "ko": 0
    },
    "percentiles4": {
        "total": 37,
        "ok": 37,
        "ko": 0
    },
    "group1": {
    "name": "t < 800 ms",
    "count": 4,
    "percentage": 100
},
    "group2": {
    "name": "t ≥ 800 ms <br> t < 1200 ms",
    "count": 0,
    "percentage": 0
},
    "group3": {
    "name": "t ≥ 1200 ms",
    "count": 0,
    "percentage": 0
},
    "group4": {
    "name": "failed",
    "count": 0,
    "percentage": 0
},
    "meanNumberOfRequestsPerSecond": {
        "total": 0.16,
        "ok": 0.16,
        "ko": 0
    }
}
    },"req_create-new-game-98820": {
        "type": "REQUEST",
        "name": "Create New Game - Gran Turismo 3",
"path": "Create New Game - Gran Turismo 3",
"pathFormatted": "req_create-new-game-98820",
"stats": {
    "name": "Create New Game - Gran Turismo 3",
    "numberOfRequests": {
        "total": 1,
        "ok": 1,
        "ko": 0
    },
    "minResponseTime": {
        "total": 25,
        "ok": 25,
        "ko": 0
    },
    "maxResponseTime": {
        "total": 25,
        "ok": 25,
        "ko": 0
    },
    "meanResponseTime": {
        "total": 25,
        "ok": 25,
        "ko": 0
    },
    "standardDeviation": {
        "total": 0,
        "ok": 0,
        "ko": 0
    },
    "percentiles1": {
        "total": 25,
        "ok": 25,
        "ko": 0
    },
    "percentiles2": {
        "total": 25,
        "ok": 25,
        "ko": 0
    },
    "percentiles3": {
        "total": 25,
        "ok": 25,
        "ko": 0
    },
    "percentiles4": {
        "total": 25,
        "ok": 25,
        "ko": 0
    },
    "group1": {
    "name": "t < 800 ms",
    "count": 1,
    "percentage": 100
},
    "group2": {
    "name": "t ≥ 800 ms <br> t < 1200 ms",
    "count": 0,
    "percentage": 0
},
    "group3": {
    "name": "t ≥ 1200 ms",
    "count": 0,
    "percentage": 0
},
    "group4": {
    "name": "failed",
    "count": 0,
    "percentage": 0
},
    "meanNumberOfRequestsPerSecond": {
        "total": 0.04,
        "ok": 0.04,
        "ko": 0
    }
}
    },"req_get-single-game-3ad46": {
        "type": "REQUEST",
        "name": "Get single game - Super Mario 64",
"path": "Get single game - Super Mario 64",
"pathFormatted": "req_get-single-game-3ad46",
"stats": {
    "name": "Get single game - Super Mario 64",
    "numberOfRequests": {
        "total": 2,
        "ok": 2,
        "ko": 0
    },
    "minResponseTime": {
        "total": 21,
        "ok": 21,
        "ko": 0
    },
    "maxResponseTime": {
        "total": 23,
        "ok": 23,
        "ko": 0
    },
    "meanResponseTime": {
        "total": 22,
        "ok": 22,
        "ko": 0
    },
    "standardDeviation": {
        "total": 1,
        "ok": 1,
        "ko": 0
    },
    "percentiles1": {
        "total": 22,
        "ok": 22,
        "ko": 0
    },
    "percentiles2": {
        "total": 23,
        "ok": 23,
        "ko": 0
    },
    "percentiles3": {
        "total": 23,
        "ok": 23,
        "ko": 0
    },
    "percentiles4": {
        "total": 23,
        "ok": 23,
        "ko": 0
    },
    "group1": {
    "name": "t < 800 ms",
    "count": 2,
    "percentage": 100
},
    "group2": {
    "name": "t ≥ 800 ms <br> t < 1200 ms",
    "count": 0,
    "percentage": 0
},
    "group3": {
    "name": "t ≥ 1200 ms",
    "count": 0,
    "percentage": 0
},
    "group4": {
    "name": "failed",
    "count": 0,
    "percentage": 0
},
    "meanNumberOfRequestsPerSecond": {
        "total": 0.08,
        "ok": 0.08,
        "ko": 0
    }
}
    },"req_delete-game---t-c965e": {
        "type": "REQUEST",
        "name": "Delete game - Tetris",
"path": "Delete game - Tetris",
"pathFormatted": "req_delete-game---t-c965e",
"stats": {
    "name": "Delete game - Tetris",
    "numberOfRequests": {
        "total": 4,
        "ok": 4,
        "ko": 0
    },
    "minResponseTime": {
        "total": 28,
        "ok": 28,
        "ko": 0
    },
    "maxResponseTime": {
        "total": 34,
        "ok": 34,
        "ko": 0
    },
    "meanResponseTime": {
        "total": 30,
        "ok": 30,
        "ko": 0
    },
    "standardDeviation": {
        "total": 2,
        "ok": 2,
        "ko": 0
    },
    "percentiles1": {
        "total": 29,
        "ok": 29,
        "ko": 0
    },
    "percentiles2": {
        "total": 30,
        "ok": 30,
        "ko": 0
    },
    "percentiles3": {
        "total": 33,
        "ok": 33,
        "ko": 0
    },
    "percentiles4": {
        "total": 34,
        "ok": 34,
        "ko": 0
    },
    "group1": {
    "name": "t < 800 ms",
    "count": 4,
    "percentage": 100
},
    "group2": {
    "name": "t ≥ 800 ms <br> t < 1200 ms",
    "count": 0,
    "percentage": 0
},
    "group3": {
    "name": "t ≥ 1200 ms",
    "count": 0,
    "percentage": 0
},
    "group4": {
    "name": "failed",
    "count": 0,
    "percentage": 0
},
    "meanNumberOfRequestsPerSecond": {
        "total": 0.16,
        "ok": 0.16,
        "ko": 0
    }
}
    },"req_get-single-game-c0088": {
        "type": "REQUEST",
        "name": "Get single game - Gran Turismo 3",
"path": "Get single game - Gran Turismo 3",
"pathFormatted": "req_get-single-game-c0088",
"stats": {
    "name": "Get single game - Gran Turismo 3",
    "numberOfRequests": {
        "total": 1,
        "ok": 1,
        "ko": 0
    },
    "minResponseTime": {
        "total": 22,
        "ok": 22,
        "ko": 0
    },
    "maxResponseTime": {
        "total": 22,
        "ok": 22,
        "ko": 0
    },
    "meanResponseTime": {
        "total": 22,
        "ok": 22,
        "ko": 0
    },
    "standardDeviation": {
        "total": 0,
        "ok": 0,
        "ko": 0
    },
    "percentiles1": {
        "total": 22,
        "ok": 22,
        "ko": 0
    },
    "percentiles2": {
        "total": 22,
        "ok": 22,
        "ko": 0
    },
    "percentiles3": {
        "total": 22,
        "ok": 22,
        "ko": 0
    },
    "percentiles4": {
        "total": 22,
        "ok": 22,
        "ko": 0
    },
    "group1": {
    "name": "t < 800 ms",
    "count": 1,
    "percentage": 100
},
    "group2": {
    "name": "t ≥ 800 ms <br> t < 1200 ms",
    "count": 0,
    "percentage": 0
},
    "group3": {
    "name": "t ≥ 1200 ms",
    "count": 0,
    "percentage": 0
},
    "group4": {
    "name": "failed",
    "count": 0,
    "percentage": 0
},
    "meanNumberOfRequestsPerSecond": {
        "total": 0.04,
        "ok": 0.04,
        "ko": 0
    }
}
    },"req_delete-game---s-4a098": {
        "type": "REQUEST",
        "name": "Delete game - Super Mario 64",
"path": "Delete game - Super Mario 64",
"pathFormatted": "req_delete-game---s-4a098",
"stats": {
    "name": "Delete game - Super Mario 64",
    "numberOfRequests": {
        "total": 2,
        "ok": 2,
        "ko": 0
    },
    "minResponseTime": {
        "total": 29,
        "ok": 29,
        "ko": 0
    },
    "maxResponseTime": {
        "total": 30,
        "ok": 30,
        "ko": 0
    },
    "meanResponseTime": {
        "total": 30,
        "ok": 30,
        "ko": 0
    },
    "standardDeviation": {
        "total": 1,
        "ok": 1,
        "ko": 0
    },
    "percentiles1": {
        "total": 30,
        "ok": 30,
        "ko": 0
    },
    "percentiles2": {
        "total": 30,
        "ok": 30,
        "ko": 0
    },
    "percentiles3": {
        "total": 30,
        "ok": 30,
        "ko": 0
    },
    "percentiles4": {
        "total": 30,
        "ok": 30,
        "ko": 0
    },
    "group1": {
    "name": "t < 800 ms",
    "count": 2,
    "percentage": 100
},
    "group2": {
    "name": "t ≥ 800 ms <br> t < 1200 ms",
    "count": 0,
    "percentage": 0
},
    "group3": {
    "name": "t ≥ 1200 ms",
    "count": 0,
    "percentage": 0
},
    "group4": {
    "name": "failed",
    "count": 0,
    "percentage": 0
},
    "meanNumberOfRequestsPerSecond": {
        "total": 0.08,
        "ok": 0.08,
        "ko": 0
    }
}
    },"req_create-new-game-fa629": {
        "type": "REQUEST",
        "name": "Create New Game - Resident Evil 4",
"path": "Create New Game - Resident Evil 4",
"pathFormatted": "req_create-new-game-fa629",
"stats": {
    "name": "Create New Game - Resident Evil 4",
    "numberOfRequests": {
        "total": 5,
        "ok": 5,
        "ko": 0
    },
    "minResponseTime": {
        "total": 25,
        "ok": 25,
        "ko": 0
    },
    "maxResponseTime": {
        "total": 35,
        "ok": 35,
        "ko": 0
    },
    "meanResponseTime": {
        "total": 29,
        "ok": 29,
        "ko": 0
    },
    "standardDeviation": {
        "total": 4,
        "ok": 4,
        "ko": 0
    },
    "percentiles1": {
        "total": 27,
        "ok": 27,
        "ko": 0
    },
    "percentiles2": {
        "total": 30,
        "ok": 30,
        "ko": 0
    },
    "percentiles3": {
        "total": 34,
        "ok": 34,
        "ko": 0
    },
    "percentiles4": {
        "total": 35,
        "ok": 35,
        "ko": 0
    },
    "group1": {
    "name": "t < 800 ms",
    "count": 5,
    "percentage": 100
},
    "group2": {
    "name": "t ≥ 800 ms <br> t < 1200 ms",
    "count": 0,
    "percentage": 0
},
    "group3": {
    "name": "t ≥ 1200 ms",
    "count": 0,
    "percentage": 0
},
    "group4": {
    "name": "failed",
    "count": 0,
    "percentage": 0
},
    "meanNumberOfRequestsPerSecond": {
        "total": 0.2,
        "ok": 0.2,
        "ko": 0
    }
}
    },"req_delete-game---g-5b459": {
        "type": "REQUEST",
        "name": "Delete game - Gran Turismo 3",
"path": "Delete game - Gran Turismo 3",
"pathFormatted": "req_delete-game---g-5b459",
"stats": {
    "name": "Delete game - Gran Turismo 3",
    "numberOfRequests": {
        "total": 1,
        "ok": 1,
        "ko": 0
    },
    "minResponseTime": {
        "total": 27,
        "ok": 27,
        "ko": 0
    },
    "maxResponseTime": {
        "total": 27,
        "ok": 27,
        "ko": 0
    },
    "meanResponseTime": {
        "total": 27,
        "ok": 27,
        "ko": 0
    },
    "standardDeviation": {
        "total": 0,
        "ok": 0,
        "ko": 0
    },
    "percentiles1": {
        "total": 27,
        "ok": 27,
        "ko": 0
    },
    "percentiles2": {
        "total": 27,
        "ok": 27,
        "ko": 0
    },
    "percentiles3": {
        "total": 27,
        "ok": 27,
        "ko": 0
    },
    "percentiles4": {
        "total": 27,
        "ok": 27,
        "ko": 0
    },
    "group1": {
    "name": "t < 800 ms",
    "count": 1,
    "percentage": 100
},
    "group2": {
    "name": "t ≥ 800 ms <br> t < 1200 ms",
    "count": 0,
    "percentage": 0
},
    "group3": {
    "name": "t ≥ 1200 ms",
    "count": 0,
    "percentage": 0
},
    "group4": {
    "name": "failed",
    "count": 0,
    "percentage": 0
},
    "meanNumberOfRequestsPerSecond": {
        "total": 0.04,
        "ok": 0.04,
        "ko": 0
    }
}
    },"req_get-single-game-7d9ba": {
        "type": "REQUEST",
        "name": "Get single game - Resident Evil 4",
"path": "Get single game - Resident Evil 4",
"pathFormatted": "req_get-single-game-7d9ba",
"stats": {
    "name": "Get single game - Resident Evil 4",
    "numberOfRequests": {
        "total": 5,
        "ok": 5,
        "ko": 0
    },
    "minResponseTime": {
        "total": 20,
        "ok": 20,
        "ko": 0
    },
    "maxResponseTime": {
        "total": 31,
        "ok": 31,
        "ko": 0
    },
    "meanResponseTime": {
        "total": 26,
        "ok": 26,
        "ko": 0
    },
    "standardDeviation": {
        "total": 5,
        "ok": 5,
        "ko": 0
    },
    "percentiles1": {
        "total": 27,
        "ok": 27,
        "ko": 0
    },
    "percentiles2": {
        "total": 30,
        "ok": 30,
        "ko": 0
    },
    "percentiles3": {
        "total": 31,
        "ok": 31,
        "ko": 0
    },
    "percentiles4": {
        "total": 31,
        "ok": 31,
        "ko": 0
    },
    "group1": {
    "name": "t < 800 ms",
    "count": 5,
    "percentage": 100
},
    "group2": {
    "name": "t ≥ 800 ms <br> t < 1200 ms",
    "count": 0,
    "percentage": 0
},
    "group3": {
    "name": "t ≥ 1200 ms",
    "count": 0,
    "percentage": 0
},
    "group4": {
    "name": "failed",
    "count": 0,
    "percentage": 0
},
    "meanNumberOfRequestsPerSecond": {
        "total": 0.2,
        "ok": 0.2,
        "ko": 0
    }
}
    },"req_delete-game---r-b9458": {
        "type": "REQUEST",
        "name": "Delete game - Resident Evil 4",
"path": "Delete game - Resident Evil 4",
"pathFormatted": "req_delete-game---r-b9458",
"stats": {
    "name": "Delete game - Resident Evil 4",
    "numberOfRequests": {
        "total": 4,
        "ok": 4,
        "ko": 0
    },
    "minResponseTime": {
        "total": 33,
        "ok": 33,
        "ko": 0
    },
    "maxResponseTime": {
        "total": 37,
        "ok": 37,
        "ko": 0
    },
    "meanResponseTime": {
        "total": 35,
        "ok": 35,
        "ko": 0
    },
    "standardDeviation": {
        "total": 1,
        "ok": 1,
        "ko": 0
    },
    "percentiles1": {
        "total": 35,
        "ok": 35,
        "ko": 0
    },
    "percentiles2": {
        "total": 36,
        "ok": 36,
        "ko": 0
    },
    "percentiles3": {
        "total": 37,
        "ok": 37,
        "ko": 0
    },
    "percentiles4": {
        "total": 37,
        "ok": 37,
        "ko": 0
    },
    "group1": {
    "name": "t < 800 ms",
    "count": 4,
    "percentage": 100
},
    "group2": {
    "name": "t ≥ 800 ms <br> t < 1200 ms",
    "count": 0,
    "percentage": 0
},
    "group3": {
    "name": "t ≥ 1200 ms",
    "count": 0,
    "percentage": 0
},
    "group4": {
    "name": "failed",
    "count": 0,
    "percentage": 0
},
    "meanNumberOfRequestsPerSecond": {
        "total": 0.16,
        "ok": 0.16,
        "ko": 0
    }
}
    }
}

}